{
  "playlists": [
    {
      "name": "Hindi Fav",
      "lastModifiedDate": "2023-11-16",
      "items": [
        {
          "track": {
            "trackName": "Saibo",
            "artistName": "Sachin-Jigar",
            "albumName": "Shor in the City (Original Motion Picture Soundtrack)",
            "trackUri": "spotify:track:6udC4b4jOSnHb9ItnXgKLR"
          },
          "episode": null,
          "localTrack": null,
          "addedDate": "2023-11-16"
        },
        {
          "track": {
            "trackName": "Raabta",
            "artistName": "Pritam",
            "albumName": "Agent Vinod",
            "trackUri": "spotify:track:6FjbAnaPRPwiP3sciEYctO"
          },
          "episode": null,
          "localTrack": null,
          "addedDate": "2023-11-16"
        },
        {
          "track": {
            "trackName": "Pee Loon",
            "artistName": "Pritam",
            "albumName": "Once Upon A Time In Mumbaai",
            "trackUri": "spotify:track:52itZ0w0CydihB2JCZEIft"
          },
          "episode": null,
          "localTrack": null,
          "addedDate": "2023-11-16"
        },
        {
          "track": {
            "trackName": "Khuda Jaane",
            "artistName": "Vishal-Shekhar",
            "albumName": "Bachna Ae Haseeno",
            "trackUri": "spotify:track:0gPgdRfB4jdGrlyXS0Vx78"
          },
          "episode": null,
          "localTrack": null,
          "addedDate": "2023-11-16"
        },
        {
          "track": {
            "trackName": "Subhanallah",
            "artistName": "Pritam",
            "albumName": "Yeh Jawaani Hai Deewani",
            "trackUri": "spotify:track:0GQngE2rOYvlKwEQjTAsP8"
          },
          "episode": null,
          "localTrack": null,
          "addedDate": "2023-11-16"
        },
        {
          "track": {
            "trackName": "Khairiyat",
            "artistName": "Pritam",
            "albumName": "Chhichhore",
            "trackUri": "spotify:track:5O932cZmzOZGOGZz9RHx20"
          },
          "episode": null,
          "localTrack": null,
          "addedDate": "2023-11-16"
        },
        {
          "track": {
            "trackName": "Jeena Jeena",
            "artistName": "Atif Aslam",
            "albumName": "Badlapur (Original Motion Picture Soundtrack)",
            "trackUri": "spotify:track:2GXXZFUxYg2LvG8SR0byOE"
          },
          "episode": null,
          "localTrack": null,
          "addedDate": "2023-11-16"
        },
        {
          "track": {
            "trackName": "Hawayein",
            "artistName": "Pritam",
            "albumName": "Jab Harry Met Sejal (Original Motion Picture Soundtrack)",
            "trackUri": "spotify:track:0l6g8Z8mqGbGXFOjigYetD"
          },
          "episode": null,
          "localTrack": null,
          "addedDate": "2023-11-16"
        },
        {
          "track": {
            "trackName": "Kabira",
            "artistName": "Pritam",
            "albumName": "Yeh Jawaani Hai Deewani",
            "trackUri": "spotify:track:4bD9z9qa4qg9BhryvYWB7c"
          },
          "episode": null,
          "localTrack": null,
          "addedDate": "2023-11-16"
        },
        {
          "track": {
            "trackName": "Tum Se Hi",
            "artistName": "Pritam",
            "albumName": "Jab We Met",
            "trackUri": "spotify:track:7eQl3Yqv35ioqUfveKHitE"
          },
          "episode": null,
          "localTrack": null,
          "addedDate": "2023-11-16"
        },
        {
          "track": {
            "trackName": "Tu Jaane Na",
            "artistName": "Atif Aslam",
            "albumName": "Best of Romance: Atif Aslam & Pritam",
            "trackUri": "spotify:track:5vGiuYFSGekGLgbxhV1rD5"
          },
          "episode": null,
          "localTrack": null,
          "addedDate": "2023-11-16"
        },
        {
          "track": {
            "trackName": "Kaise Hua (From \"Kabir Singh\")",
            "artistName": "Vishal Mishra",
            "albumName": "Kaise Hua (From \"Kabir Singh\")",
            "trackUri": "spotify:track:1y1rQTkWmrZdJmjwuK07GC"
          },
          "episode": null,
          "localTrack": null,
          "addedDate": "2023-11-16"
        },
        {
          "track": {
            "trackName": "Ik Vaari Aa (From \"Raabta\")",
            "artistName": "Pritam",
            "albumName": "Ik Vaari Aa (From \"Raabta\")",
            "trackUri": "spotify:track:5lrA2NzUxmBjKr2tCZfMtl"
          },
          "episode": null,
          "localTrack": null,
          "addedDate": "2023-11-16"
        },
        {
          "track": {
            "trackName": "Pehli Nazar Mein",
            "artistName": "Atif Aslam",
            "albumName": "Best of Romance: Atif Aslam & Pritam",
            "trackUri": "spotify:track:5llaVhaIoowKT3fqf2NfPO"
          },
          "episode": null,
          "localTrack": null,
          "addedDate": "2023-11-16"
        },
        {
          "track": {
            "trackName": "Aankhon Se Batana",
            "artistName": "Dikshant",
            "albumName": "Aankhon Se Batana",
            "trackUri": "spotify:track:1ZiReD9pPTttQWwSoYqdyH"
          },
          "episode": null,
          "localTrack": null,
          "addedDate": "2023-11-16"
        },
        {
          "track": {
            "trackName": "Saware (From \"Phantom\")",
            "artistName": "Arijit Singh",
            "albumName": "Ultimate Love Songs - Arijit Singh",
            "trackUri": "spotify:track:2y0hUGvHaKm2p5xmJF4HBe"
          },
          "episode": null,
          "localTrack": null,
          "addedDate": "2023-11-16"
        },
        {
          "track": {
            "trackName": "Choo Lo",
            "artistName": "The Local Train",
            "albumName": "Aalas Ka Pedh",
            "trackUri": "spotify:track:2qgXrzJsry4KgYoJCpuaul"
          },
          "episode": null,
          "localTrack": null,
          "addedDate": "2023-11-16"
        },
        {
          "track": {
            "trackName": "Zara Sa",
            "artistName": "Pritam",
            "albumName": "Jannat (Original Motion Picture Soundtrack)",
            "trackUri": "spotify:track:18YHbIhrleUkKKj2DvEp79"
          },
          "episode": null,
          "localTrack": null,
          "addedDate": "2023-11-16"
        },
        {
          "track": {
            "trackName": "Kya Mujhe Pyar Hai (From \"Woh Lamhe\")",
            "artistName": "KK",
            "albumName": "Evergreen Hits Of K.K.",
            "trackUri": "spotify:track:7fW9J3EpVWVN1ouv0slAs0"
          },
          "episode": null,
          "localTrack": null,
          "addedDate": "2023-11-16"
        },
        {
          "track": {
            "trackName": "Raanjhanaa",
            "artistName": "A.R. Rahman",
            "albumName": "Raanjhanaa (Original Motion Picture Soundtrack)",
            "trackUri": "spotify:track:5OMUXgfXsSukZ0zxelpC3b"
          },
          "episode": null,
          "localTrack": null,
          "addedDate": "2023-11-16"
        },
        {
          "track": {
            "trackName": "Enna Sona",
            "artistName": "A.R. Rahman",
            "albumName": "OK Jaanu (Original Motion Picture Soundtrack)",
            "trackUri": "spotify:track:6bdpj89aYEBjhpsenXAsmO"
          },
          "episode": null,
          "localTrack": null,
          "addedDate": "2023-11-16"
        },
        {
          "track": {
            "trackName": "Humdard (From \"Ek Villain\")",
            "artistName": "Arijit Singh",
            "albumName": "Ultimate Love Songs - Arijit Singh",
            "trackUri": "spotify:track:2PvaburAUlhNHxVhw5lvOq"
          },
          "episode": null,
          "localTrack": null,
          "addedDate": "2023-11-16"
        },
        {
          "track": {
            "trackName": "Ilahi",
            "artistName": "Pritam",
            "albumName": "Yeh Jawaani Hai Deewani",
            "trackUri": "spotify:track:5cgKosPPj5Cs9a2JQufUc1"
          },
          "episode": null,
          "localTrack": null,
          "addedDate": "2023-11-16"
        },
        {
          "track": {
            "trackName": "Ishq Wala Love",
            "artistName": "Vishal-Shekhar",
            "albumName": "Student of the Year (Original Motion Picture Soundtrack)",
            "trackUri": "spotify:track:1hQia6rxgfM1ly2hE3StWp"
          },
          "episode": null,
          "localTrack": null,
          "addedDate": "2023-11-16"
        },
        {
          "track": {
            "trackName": "Ajab Si (From \"Om Shanti Om\")",
            "artistName": "KK",
            "albumName": "Zindagi Do Pal Ki - K.K. All Time Hits",
            "trackUri": "spotify:track:2RgvvnMwtP0R2OkVZmFvnV"
          },
          "episode": null,
          "localTrack": null,
          "addedDate": "2023-11-16"
        },
        {
          "track": {
            "trackName": "Tera Hone Laga Hoon",
            "artistName": "Atif Aslam",
            "albumName": "Best of Romance: Atif Aslam & Pritam",
            "trackUri": "spotify:track:48Ix6ReYdJf2H4mKb3TIpj"
          },
          "episode": null,
          "localTrack": null,
          "addedDate": "2023-11-16"
        },
        {
          "track": {
            "trackName": "Shayad",
            "artistName": "Pritam",
            "albumName": "Love Aaj Kal",
            "trackUri": "spotify:track:1smFN2CLqGROu0J0UyvDfL"
          },
          "episode": null,
          "localTrack": null,
          "addedDate": "2023-11-16"
        },
        {
          "track": {
            "trackName": "Chand Sifarish",
            "artistName": "Jatin-Lalit",
            "albumName": "Fanaa",
            "trackUri": "spotify:track:5EYZZvmNAH5VZCwuzYJqoA"
          },
          "episode": null,
          "localTrack": null,
          "addedDate": "2023-11-16"
        },
        {
          "track": {
            "trackName": "Mitwa",
            "artistName": "Shankar-Ehsaan-Loy",
            "albumName": "Kabhi Alvida Naa Kehna (Original Motion Picture Soundtrack)",
            "trackUri": "spotify:track:4BTPzhEsyW3blWcxcuhLM0"
          },
          "episode": null,
          "localTrack": null,
          "addedDate": "2023-11-16"
        },
        {
          "track": {
            "trackName": "Dil Diyan Gallan",
            "artistName": "Atif Aslam",
            "albumName": "YRF Top 10 - Falling in Love",
            "trackUri": "spotify:track:0FBQ4NrrHUbR9kus7rzrOj"
          },
          "episode": null,
          "localTrack": null,
          "addedDate": "2023-11-16"
        }
      ],
      "description": null,
      "numberOfFollowers": 0
    },
    {
      "name": "A Gallant Gentleman",
      "lastModifiedDate": "2023-11-15",
      "items": [
        {
          "track": {
            "trackName": "A Gallant Gentleman",
            "artistName": "We Lost The Sea",
            "albumName": "Departure Songs",
            "trackUri": "spotify:track:7MZM9KhwGQG8QJ4BycsnQn"
          },
          "episode": null,
          "localTrack": null,
          "addedDate": "2023-11-15"
        },
        {
          "track": {
            "trackName": "The Way Home",
            "artistName": "Sleep Dealer",
            "albumName": "The Way Home",
            "trackUri": "spotify:track:7GplqC9ivS2fjPFalfC2e5"
          },
          "episode": null,
          "localTrack": null,
          "addedDate": "2023-11-15"
        },
        {
          "track": {
            "trackName": "Quiet",
            "artistName": "This Will Destroy You",
            "albumName": "Young Mountain",
            "trackUri": "spotify:track:4llDF3RuBQYj2nkjTCJY4w"
          },
          "episode": null,
          "localTrack": null,
          "addedDate": "2023-11-15"
        },
        {
          "track": {
            "trackName": "Your Hand in Mine",
            "artistName": "Explosions In The Sky",
            "albumName": "The Earth Is Not a Cold Dead Place",
            "trackUri": "spotify:track:3HBcQ5GenzAlBhCIgDGL3x"
          },
          "episode": null,
          "localTrack": null,
          "addedDate": "2023-11-15"
        },
        {
          "track": {
            "trackName": "Herstory Of Glory",
            "artistName": "Do Make Say Think",
            "albumName": "You You're A History In Rust",
            "trackUri": "spotify:track:4moS7VnbiSGNzfZVVRnk8X"
          },
          "episode": null,
          "localTrack": null,
          "addedDate": "2023-11-15"
        }
      ],
      "description": null,
      "numberOfFollowers": 0
    },
    {
      "name": "2021",
      "lastModifiedDate": "2021-03-04",
      "items": [
        {
          "track": {
            "trackName": "Buttabomma - Telugu",
            "artistName": "Armaan Malik",
            "albumName": "Ala Vaikunthapurramuloo",
            "trackUri": "spotify:track:0dnDTvdUco2UbaBjUtPxNS"
          },
          "episode": null,
          "localTrack": null,
          "addedDate": "2021-03-04"
        },
        {
          "track": {
            "trackName": "The Real Slim Shady",
            "artistName": "Eminem",
            "albumName": "The Marshall Mathers LP",
            "trackUri": "spotify:track:3yfqSUWxFvZELEM4PmlwIR"
          },
          "episode": null,
          "localTrack": null,
          "addedDate": "2021-03-04"
        },
        {
          "track": {
            "trackName": "Brown Munde",
            "artistName": "AP Dhillon",
            "albumName": "Brown Munde",
            "trackUri": "spotify:track:58f4twRnbZOOVUhMUpplJ4"
          },
          "episode": null,
          "localTrack": null,
          "addedDate": "2021-03-04"
        },
        {
          "track": {
            "trackName": "Without Me",
            "artistName": "Eminem",
            "albumName": "The Eminem Show",
            "trackUri": "spotify:track:7lQ8MOhq6IN2w8EYcFNSUk"
          },
          "episode": null,
          "localTrack": null,
          "addedDate": "2021-03-04"
        }
      ],
      "description": null,
      "numberOfFollowers": 0
    },
    {
      "name": "Liked from Radio",
      "lastModifiedDate": "2019-09-24",
      "items": [
        {
          "track": {
            "trackName": "Prey",
            "artistName": "The Neighbourhood",
            "albumName": "Wiped Out!",
            "trackUri": "spotify:track:38kjFXYgPvtuXCPbHPMGte"
          },
          "episode": null,
          "localTrack": null,
          "addedDate": "2019-09-24"
        },
        {
          "track": {
            "trackName": "Hiding tonight",
            "artistName": "Alex Turner",
            "albumName": "Submarine - Original Songs From The Film By Alex Turner",
            "trackUri": "spotify:track:0x47zt71IYykbt1ET933pJ"
          },
          "episode": null,
          "localTrack": null,
          "addedDate": "2019-09-24"
        },
        {
          "track": {
            "trackName": "I Always Wanna Die (Sometimes)",
            "artistName": "The 1975",
            "albumName": "A Brief Inquiry Into Online Relationships",
            "trackUri": "spotify:track:7iPlcFvOMOzt6v0QvcAueZ"
          },
          "episode": null,
          "localTrack": null,
          "addedDate": "2019-09-24"
        },
        {
          "track": {
            "trackName": "Do Me a Favour",
            "artistName": "Arctic Monkeys",
            "albumName": "Favourite Worst Nightmare",
            "trackUri": "spotify:track:13NCxLOlvQ4Tnexgfp03Gs"
          },
          "episode": null,
          "localTrack": null,
          "addedDate": "2019-09-24"
        },
        {
          "track": {
            "trackName": "Atlas Hands",
            "artistName": "Benjamin Francis Leftwich",
            "albumName": "Last Smoke Before the Snowstorm",
            "trackUri": "spotify:track:4gSYPXqENGdaJiwm6W0hkQ"
          },
          "episode": null,
          "localTrack": null,
          "addedDate": "2019-09-17"
        },
        {
          "track": {
            "trackName": "Lisztomania",
            "artistName": "Phoenix",
            "albumName": "Wolfgang Amadeus Phoenix",
            "trackUri": "spotify:track:7hwcojGiRqYm100tSmpZE3"
          },
          "episode": null,
          "localTrack": null,
          "addedDate": "2019-09-16"
        },
        {
          "track": {
            "trackName": "Cocoon",
            "artistName": "Milky Chance",
            "albumName": "Blossom",
            "trackUri": "spotify:track:6acDlNeA06MCVCzsTVGr9V"
          },
          "episode": null,
          "localTrack": null,
          "addedDate": "2019-09-16"
        },
        {
          "track": {
            "trackName": "Cigarette Daydreams",
            "artistName": "Cage The Elephant",
            "albumName": "Melophobia",
            "trackUri": "spotify:track:2tznHmp70DxMyr2XhWLOW0"
          },
          "episode": null,
          "localTrack": null,
          "addedDate": "2019-09-16"
        },
        {
          "track": {
            "trackName": "Ten Feet Tall (Acoustic)",
            "artistName": "Corey Gray",
            "albumName": "Discovery, Vol. 6",
            "trackUri": "spotify:track:5vDoxPSSWhiZ9MAqXXkwsm"
          },
          "episode": null,
          "localTrack": null,
          "addedDate": "2019-03-15"
        },
        {
          "track": {
            "trackName": "Playinwitme",
            "artistName": "Halloran & Kate",
            "albumName": "Playinwitme",
            "trackUri": "spotify:track:4hXSBEC9pb51viFhrwBEwr"
          },
          "episode": null,
          "localTrack": null,
          "addedDate": "2019-03-15"
        },
        {
          "track": {
            "trackName": "Psycho",
            "artistName": "Sara Farell",
            "albumName": "Psycho",
            "trackUri": "spotify:track:1EvLLF8zOiXYfoPRAVP0Qq"
          },
          "episode": null,
          "localTrack": null,
          "addedDate": "2019-03-15"
        },
        {
          "track": {
            "trackName": "God is a Woman",
            "artistName": "The Mayries",
            "albumName": "God is a Woman",
            "trackUri": "spotify:track:3xm2OKIlHN2HiDA4ZxeOVo"
          },
          "episode": null,
          "localTrack": null,
          "addedDate": "2019-03-15"
        },
        {
          "track": {
            "trackName": "I Wanna Dance with Somebody",
            "artistName": "Megan Davies",
            "albumName": "I Wanna Dance with Somebody",
            "trackUri": "spotify:track:2wpebYFWzZ06RNYkOZgw6x"
          },
          "episode": null,
          "localTrack": null,
          "addedDate": "2019-03-15"
        },
        {
          "track": {
            "trackName": "Call Out My Name",
            "artistName": "Mother's Daughter",
            "albumName": "Call Out My Name",
            "trackUri": "spotify:track:4XIaUpLlWb1y3YVByVSFla"
          },
          "episode": null,
          "localTrack": null,
          "addedDate": "2019-03-15"
        },
        {
          "track": {
            "trackName": "Sick Boy",
            "artistName": "Darnell Smith",
            "albumName": "Sick Boy",
            "trackUri": "spotify:track:6e8m1rGIJUFswGLK3GAjl2"
          },
          "episode": null,
          "localTrack": null,
          "addedDate": "2019-03-14"
        },
        {
          "track": {
            "trackName": "Call Out My Name",
            "artistName": "Mother's Daughter",
            "albumName": "Call Out My Name",
            "trackUri": "spotify:track:4XIaUpLlWb1y3YVByVSFla"
          },
          "episode": null,
          "localTrack": null,
          "addedDate": "2019-03-14"
        },
        {
          "track": {
            "trackName": "Umbrella - Acoustic Version",
            "artistName": "The Mayries",
            "albumName": "Umbrella",
            "trackUri": "spotify:track:1hrDzrt4YgZdD67MOu5U0Q"
          },
          "episode": null,
          "localTrack": null,
          "addedDate": "2019-03-14"
        },
        {
          "track": {
            "trackName": "Colour",
            "artistName": "Ben Botfield",
            "albumName": "Colour",
            "trackUri": "spotify:track:6hJ0XBf7viMI5jOTtceSdP"
          },
          "episode": null,
          "localTrack": null,
          "addedDate": "2019-03-14"
        },
        {
          "track": {
            "trackName": "Habits (Stay High)",
            "artistName": "Darnell Smith",
            "albumName": "Habits (Stay High)",
            "trackUri": "spotify:track:4VQHuBY2hLAxkMyHbyXAWt"
          },
          "episode": null,
          "localTrack": null,
          "addedDate": "2019-03-14"
        },
        {
          "track": {
            "trackName": "Used To",
            "artistName": "Sandro Cavazza",
            "albumName": "Used To",
            "trackUri": "spotify:track:24qOlCdUSSU6ungmY6fZmi"
          },
          "episode": null,
          "localTrack": null,
          "addedDate": "2019-03-12"
        },
        {
          "track": {
            "trackName": "Lose You Too",
            "artistName": "shy martin",
            "albumName": "Lose You Too",
            "trackUri": "spotify:track:5JkUNbYSn06ghlmu0NRUMf"
          },
          "episode": null,
          "localTrack": null,
          "addedDate": "2019-03-12"
        },
        {
          "track": {
            "trackName": "Torn - Bonus Track",
            "artistName": "James TW",
            "albumName": "First Impressions",
            "trackUri": "spotify:track:5511Aj0mYSejKP6fplsoRk"
          },
          "episode": null,
          "localTrack": null,
          "addedDate": "2019-03-12"
        },
        {
          "track": {
            "trackName": "Lovebug",
            "artistName": "Jonas Brothers",
            "albumName": "A Little Bit Longer",
            "trackUri": "spotify:track:0JlPOiJFrlFnC5QHcLPyPV"
          },
          "episode": null,
          "localTrack": null,
          "addedDate": "2019-03-05"
        },
        {
          "track": {
            "trackName": "Gladiator",
            "artistName": "Zayde Wølf",
            "albumName": "Gladiator",
            "trackUri": "spotify:track:5ezjiqla1EIIXUOWrs2aGu"
          },
          "episode": null,
          "localTrack": null,
          "addedDate": "2019-03-04"
        },
        {
          "track": {
            "trackName": "Call Me Devil",
            "artistName": "Friends in Tokyo",
            "albumName": "Keep Moving On",
            "trackUri": "spotify:track:5VXfsQX2NYS9USmDgVyys0"
          },
          "episode": null,
          "localTrack": null,
          "addedDate": "2019-03-04"
        },
        {
          "track": {
            "trackName": "Comfortably Numb",
            "artistName": "Pink Floyd",
            "albumName": "The Wall",
            "trackUri": "spotify:track:5HNCy40Ni5BZJFw1TKzRsC"
          },
          "episode": null,
          "localTrack": null,
          "addedDate": "2019-03-04"
        },
        {
          "track": {
            "trackName": "Chosen Ones",
            "artistName": "Mountains vs. Machines",
            "albumName": "Emerge",
            "trackUri": "spotify:track:4x0UO0ngX4e6EJedgmVU13"
          },
          "episode": null,
          "localTrack": null,
          "addedDate": "2019-03-03"
        },
        {
          "track": {
            "trackName": "Rockabye - Acoustic Version",
            "artistName": "The Mayries",
            "albumName": "Rockabye",
            "trackUri": "spotify:track:30LDuVfrePWbedYTc1mUCn"
          },
          "episode": null,
          "localTrack": null,
          "addedDate": "2019-03-02"
        },
        {
          "track": {
            "trackName": "Better Than Today",
            "artistName": "Rhys Lewis",
            "albumName": "Better Than Today",
            "trackUri": "spotify:track:6MLHg35rlksBc5OBcdZvJi"
          },
          "episode": null,
          "localTrack": null,
          "addedDate": "2019-03-02"
        }
      ],
      "description": null,
      "numberOfFollowers": 0
    }
  ]
}